__init__.py
csv_converter.py
test_csv_converter.py
test_funcs.py
csv_converter-0.0.7.dist-info/LICENCE
csv_converter-0.0.7.dist-info/METADATA
csv_converter-0.0.7.dist-info/WHEEL
csv_converter-0.0.7.dist-info/top_level.txt
csv_converter-0.0.7.dist-info/RECORD
