Metadata-Version: 2.1
Name: csv-converter
Version: 0.0.7
Summary: Tool to convert CSV files based on JSON config.
Home-page: https://github.com/JWDT/csv_converter
Author: JWDT
Author-email: pypi@zephyr.ltd.uk
License: UNKNOWN
Platform: UNKNOWN
Classifier: Programming Language :: Python :: 3
Classifier: License :: OSI Approved :: MIT License
Classifier: Operating System :: OS Independent
